hoppie_connector/ADSC.py
hoppie_connector/API.py
hoppie_connector/CPDLC.py
hoppie_connector/Messages.py
hoppie_connector/Responses.py
hoppie_connector/Utilities.py
hoppie_connector/__init__.py
hoppie_connector-0.2.0.dist-info/LICENSE
hoppie_connector-0.2.0.dist-info/METADATA
hoppie_connector-0.2.0.dist-info/WHEEL
hoppie_connector-0.2.0.dist-info/top_level.txt
hoppie_connector-0.2.0.dist-info/RECORD
