Metadata-Version: 2.1
Name: hoppie-connector
Version: 0.2.0
Summary: Python connector for Hoppie's ACARS service 
Author: islandc_
License: MIT License
Project-URL: Homepage, https://islandcontroller.github.io/hoppie-connector/
Project-URL: Repository, https://github.com/islandcontroller/hoppie-connector.git
Project-URL: Issues, https://github.com/islandcontroller/hoppie-connector/issues/
Project-URL: Documentation, https://github.com/islandcontroller/hoppie-connector/wiki/
Keywords: hoppie,acars,vatsim
Classifier: Development Status :: 3 - Alpha
Classifier: Intended Audience :: Developers
Classifier: License :: OSI Approved :: MIT License
Classifier: Operating System :: OS Independent
Classifier: Programming Language :: Python :: 3
Classifier: Programming Language :: Python :: 3.12
Classifier: Topic :: Communications
Classifier: Topic :: Games/Entertainment :: Simulation
Classifier: Topic :: Software Development :: Libraries :: Application Frameworks
Classifier: Topic :: Software Development :: Libraries :: Python Modules
Requires-Python: >=3.12
License-File: LICENSE
Requires-Dist: requests >=2.31.0
Provides-Extra: test
Requires-Dist: pytest >=8.1 ; extra == 'test'
Requires-Dist: pytest-cov >=4.1 ; extra == 'test'
Requires-Dist: responses >=0.25 ; extra == 'test'
Requires-Dist: ruff >=0.3 ; extra == 'test'
